physiboss_models/__init__.py
physiboss_models/models.py
physiboss_models-0.1.2.dist-info/licenses/LICENSE
physiboss_models-0.1.2.dist-info/METADATA
physiboss_models-0.1.2.dist-info/WHEEL
physiboss_models-0.1.2.dist-info/top_level.txt
physiboss_models-0.1.2.dist-info/RECORD
