Metadata-Version: 2.4
Name: physiboss_models
Version: 0.1.2
Summary: Library for using PhysiBoSS-Models
Author-email: Vincent Noël <vincent.noel@curie.fr>
License-Expression: MIT
Project-URL: Homepage, https://github.com/PhysiBoSS/PhysiBoSS-Models
Project-URL: Repository, https://github.com/PhysiBoSS/PhysiBoSS-Models
Project-URL: Issues, https://github.com/PhysiBoSS/PhysiBoSS-Models/issues
Requires-Python: >3.8
License-File: LICENSE
Requires-Dist: PyGithub
Requires-Dist: PyYaml
Dynamic: license-file
